devtools/__init__.py
devtools/chrome-wrapper.sh
devtools/proxy.py
devtools_proxy-0.1.0.dist-info/DESCRIPTION.rst
devtools_proxy-0.1.0.dist-info/METADATA
devtools_proxy-0.1.0.dist-info/RECORD
devtools_proxy-0.1.0.dist-info/WHEEL
devtools_proxy-0.1.0.dist-info/entry_points.txt
devtools_proxy-0.1.0.dist-info/metadata.json
devtools_proxy-0.1.0.dist-info/top_level.txt
