Metadata-Version: 2.0
Name: devtools-proxy
Version: 0.1.0
Summary: DevTools Proxy
Home-page: https://github.com/bayandin/devtools-proxy
Author: Alexander Bayandin
Author-email: a.bayandin@gmail.com
License: MIT
Keywords: selenium chrome chromedriver devtools
Platform: UNKNOWN
Classifier: Development Status :: 3 - Alpha
Classifier: Intended Audience :: Developers
Classifier: License :: OSI Approved :: MIT License
Classifier: Operating System :: MacOS :: MacOS X
Classifier: Operating System :: POSIX
Classifier: Programming Language :: Python
Classifier: Programming Language :: Python :: 3.6
Classifier: Topic :: Software Development :: Testing
Requires-Dist: aiohttp (==2.2.5)
Requires-Dist: cchardet (==2.1.1)
Requires-Dist: ujson (==1.35)
Requires-Dist: uvloop (==0.8.1)
